odoo8_addon_website_upload_video-8.0.1.0.0.99.dev13-py2.7-nspkg.pth
odoo8_addon_website_upload_video-8.0.1.0.0.99.dev13.dist-info/METADATA
odoo8_addon_website_upload_video-8.0.1.0.0.99.dev13.dist-info/RECORD
odoo8_addon_website_upload_video-8.0.1.0.0.99.dev13.dist-info/WHEEL
odoo8_addon_website_upload_video-8.0.1.0.0.99.dev13.dist-info/namespace_packages.txt
odoo8_addon_website_upload_video-8.0.1.0.0.99.dev13.dist-info/top_level.txt
odoo_addons/website_upload_video/README.rst
odoo_addons/website_upload_video/__init__.py
odoo_addons/website_upload_video/__openerp__.py
odoo_addons/website_upload_video/controllers/__init__.py
odoo_addons/website_upload_video/controllers/main.py
odoo_addons/website_upload_video/i18n/fr.po
odoo_addons/website_upload_video/i18n/it.po
odoo_addons/website_upload_video/i18n/sl.po
odoo_addons/website_upload_video/i18n/website_upload_video.pot
odoo_addons/website_upload_video/static/description/icon.png
odoo_addons/website_upload_video/static/src/js/website_upload_video.js
odoo_addons/website_upload_video/static/src/xml/website_upload_video.xml
odoo_addons/website_upload_video/views/website_upload_video_views.xml
